FoxDotEditor/AppFunctions.py
FoxDotEditor/BracketHandler.py
FoxDotEditor/Console.py
FoxDotEditor/Editor.py
FoxDotEditor/EditorSettings.py
FoxDotEditor/Format.py
FoxDotEditor/LineNumbers.py
FoxDotEditor/MenuBar.py
FoxDotEditor/Preferences.py
FoxDotEditor/Prompt.py
FoxDotEditor/SampleChart.py
FoxDotEditor/SearchBar.py
FoxDotEditor/TextBox.py
FoxDotEditor/Treeview.py
FoxDotEditor/__main__.py
FoxDotEditor/tkimport.py
FoxDotEditor/img/file.png
FoxDotEditor/img/folder.png
FoxDotEditor/img/foxdot.ico
FoxDotEditor/img/icon.gif
FoxDotEditor/img/icon.ico
FoxDotEditor/img/treeview_icons.svg
FoxDotEditor/themes/cerulean.json
FoxDotEditor/themes/cosmos.json
FoxDotEditor/themes/cyborg.json
FoxDotEditor/themes/darkly.json
FoxDotEditor/themes/default.json
FoxDotEditor/themes/dracula.json
FoxDotEditor/themes/flatly.json
FoxDotEditor/themes/gruvbox.json
FoxDotEditor/themes/journal.json
FoxDotEditor/themes/lumen.json
FoxDotEditor/themes/material.json
FoxDotEditor/themes/monokai.json
FoxDotEditor/themes/nord.json
FoxDotEditor/themes/one_dark.json
FoxDotEditor/themes/outdoors.json
FoxDotEditor/themes/paper.json
FoxDotEditor/themes/readable.json
FoxDotEditor/themes/sandstone.json
FoxDotEditor/themes/simplex.json
FoxDotEditor/themes/slate.json
FoxDotEditor/themes/solarized_dark.json
FoxDotEditor/themes/spacelab.json
FoxDotEditor/themes/united.json
FoxDotEditor/tmp/__init__.py
FoxDotEditor/tmp/tempfile.txt
FoxDotEditor-0.9.13.dist-info/METADATA
FoxDotEditor-0.9.13.dist-info/WHEEL
FoxDotEditor-0.9.13.dist-info/entry_points.txt
FoxDotEditor-0.9.13.dist-info/top_level.txt
FoxDotEditor-0.9.13.dist-info/RECORD
