Metadata-Version: 2.1
Name: FoxDotEditor
Version: 0.9.13
Summary: Original FoxDot editor extracted from FoxDot Project - Live coding music with SuperCollider
Home-page: http://foxdot.org/
Author: Elie Gavoty
Author-email: eliegavoty@free.fr
License: cc-by-sa-4.0
Requires-Dist: renardo-lib ==0.9.13
Requires-Dist: renardo-gatherer ==0.1.4.dev1
Requires-Dist: psutil
Requires-Dist: ttkbootstrap ==1.10.1
